fmu_settings_api/__init__.py
fmu_settings_api/__main__.py
fmu_settings_api/_version.py
fmu_settings_api/config.py
fmu_settings_api/logging.py
fmu_settings_api/py.typed
fmu_settings_api/session.py
fmu_settings_api/deps/__init__.py
fmu_settings_api/deps/auth.py
fmu_settings_api/deps/mappings.py
fmu_settings_api/deps/match.py
fmu_settings_api/deps/permissions.py
fmu_settings_api/deps/project.py
fmu_settings_api/deps/resource.py
fmu_settings_api/deps/rms.py
fmu_settings_api/deps/session.py
fmu_settings_api/deps/smda.py
fmu_settings_api/deps/user_fmu.py
fmu_settings_api/interfaces/__init__.py
fmu_settings_api/interfaces/smda_api.py
fmu_settings_api/middleware/__init__.py
fmu_settings_api/middleware/logging.py
fmu_settings_api/models/__init__.py
fmu_settings_api/models/common.py
fmu_settings_api/models/match.py
fmu_settings_api/models/project.py
fmu_settings_api/models/resource.py
fmu_settings_api/models/rms.py
fmu_settings_api/models/session.py
fmu_settings_api/models/smda.py
fmu_settings_api/services/__init__.py
fmu_settings_api/services/mappings.py
fmu_settings_api/services/match.py
fmu_settings_api/services/project.py
fmu_settings_api/services/resource.py
fmu_settings_api/services/rms.py
fmu_settings_api/services/session.py
fmu_settings_api/services/smda.py
fmu_settings_api/services/user.py
fmu_settings_api/v1/__init__.py
fmu_settings_api/v1/main.py
fmu_settings_api/v1/responses.py
fmu_settings_api/v1/routes/__init__.py
fmu_settings_api/v1/routes/match.py
fmu_settings_api/v1/routes/project.py
fmu_settings_api/v1/routes/rms.py
fmu_settings_api/v1/routes/session.py
fmu_settings_api/v1/routes/user.py
fmu_settings_api/v1/routes/smda/__init__.py
fmu_settings_api/v1/routes/smda/main.py
fmu_settings_api-0.6.0.dist-info/licenses/LICENSE
fmu_settings_api-0.6.0.dist-info/METADATA
fmu_settings_api-0.6.0.dist-info/WHEEL
fmu_settings_api-0.6.0.dist-info/top_level.txt
fmu_settings_api-0.6.0.dist-info/RECORD
