Metadata-Version: 2.4
Name: fmu-settings-api
Version: 0.6.0
Summary: The API for fmu-settings
Author-email: Equinor <fg-fmu_atlas@equinor.com>
License: GPL-3.0
Project-URL: Homepage, https://github.com/equinor/fmu-settings-api
Project-URL: Repository, https://github.com/equinor/fmu-settings-api
Project-URL: Documentation, https://github.com/equinor/fmu-settings-api
Classifier: Development Status :: 3 - Alpha
Classifier: Topic :: Scientific/Engineering
Classifier: Topic :: Utilities
Classifier: Operating System :: POSIX :: Linux
Classifier: Programming Language :: Python :: 3.11
Classifier: Programming Language :: Python :: 3.12
Classifier: Natural Language :: English
Requires-Python: >=3.11
License-File: LICENSE
Requires-Dist: fastapi
Requires-Dist: fmu-datamodels
Requires-Dist: fmu-settings>=0.18.0
Requires-Dist: httpx
Requires-Dist: packaging
Requires-Dist: pydantic
Requires-Dist: pyyaml
Requires-Dist: rapidfuzz>=3.0.0
Requires-Dist: runrms>=0.7.3
Requires-Dist: structlog
Requires-Dist: uvicorn
Provides-Extra: dev
Requires-Dist: python-dotenv; extra == "dev"
Requires-Dist: mypy; extra == "dev"
Requires-Dist: pytest; extra == "dev"
Requires-Dist: pytest-asyncio; extra == "dev"
Requires-Dist: pytest-cov; extra == "dev"
Requires-Dist: pytest-mock; extra == "dev"
Requires-Dist: pytest-xdist; extra == "dev"
Requires-Dist: ruff; extra == "dev"
Requires-Dist: types-PyYAML; extra == "dev"
Requires-Dist: types-requests; extra == "dev"
Requires-Dist: watchfiles; extra == "dev"
Requires-Dist: fmu-settings-cli; extra == "dev"
Dynamic: license-file
